{"title":"Play Your Position","year":"2014","rated":"N/A","released":"26 Apr 2014","runtime":"N/A","genre":"Comedy","director":"Bennie Randall Jr.","writer":"Bennie Randall Jr.","actors":"Bennie Randall Jr., Sixx Desjardins, Cuba Lezcan, Troy Wright","plot":"Three friends who have no clue about how to make relationships work, are having a hard time dealing with the women they love.","language":"English","country":"USA","awards":"N/A","metascore":"N/A","type":"movie","id":"8c816552-01fb-4047-b7d7-84b5e5075c31"}
