{"title":"Feed Me with Your Words","year":"2012","rated":"N/A","released":"28 Feb 2013","runtime":"88 min","genre":"Drama","director":"Martin Turk","writer":"Franz Rodenkirchen (script editor), Martin Turk","actors":"Sebastian Cavazza, Jure Henigman, Boris Cavazza, Masa Derganc","plot":"The disappearance of the younger son, forces a family to look into the past and confront the reasons of why the present has become as it is.","language":"Slovenian, Italian","country":"Slovenia","awards":"3 nominations.","metascore":"N/A","type":"movie","id":"d0d7d413-1a27-41b6-8364-d0d771357e06"}
